pytest_checklist/__about__.py
pytest_checklist/__init__.py
pytest_checklist/app.py
pytest_checklist/collector.py
pytest_checklist/defaults.py
pytest_checklist/path_utils.py
pytest_checklist/plugin.py
pytest_checklist/pointer.py
pytest_checklist/report.py
pytest_checklist-0.3.7.dist-info/METADATA
pytest_checklist-0.3.7.dist-info/WHEEL
pytest_checklist-0.3.7.dist-info/entry_points.txt
pytest_checklist-0.3.7.dist-info/licenses/LICENSE
pytest_checklist-0.3.7.dist-info/RECORD
