Metadata-Version: 2.4
Name: pytest-checklist
Version: 0.3.7
Summary: Pytest plugin to track and report unit/function coverage.
Project-URL: repository, https://github.com/examol-corp/pytest-checklist
Project-URL: homepage, https://github.com/examol-corp/pytest-checklist
Author: Jack Klimov
Author-email: Samuel Lotz <salotz@salotz.info>
Maintainer-email: Samuel Lotz <salotz@salotz.info>
License-Expression: MIT
License-File: LICENSE
Keywords: plugin,pytest,unit test
Requires-Python: >=3.10
Requires-Dist: libcst
Requires-Dist: rich
